{
    "user": {
        "objectclasses": [
            "top", 
            "person", 
            "organizationalPerson", 
            "inetOrgPerson"
        ],
        "mappings": {
            "cn": "name",
            "departmentnumber": "department",
            "displayname": "name",
            "employeenumber": "employeenumber",
            "facsimiletelephonenumber": "fax",
            "givenname": "firstname",
            "mail": "email",
            "mobile": "mobilephone",
            "postalcode": "postalcode",
            "preferredlanguage": "localesidkey",
            "sn": "lastname",
            "telephonenumber": "phone",
            "title": "title",
            "uid": "id"
        }
    }, 
    "contact": {
        "objectclasses": [
            "top", 
            "person", 
            "organizationalPerson", 
            "inetOrgPerson"
        ],
        "mappings": {
            "cn": "name",
            "departmentnumber": "department",
            "description": "description",
            "displayname": "name",
            "facsimiletelephonenumber": "fax",
            "givenname": "firstname",
            "homephone": "homephone", 
            "mail": "email",
            "mobile": "mobilephone",
            "telephonenumber": "phone",
            "title": "title",
            "sn": "lastname",
            "uid": "id"
        }
    },
    "lead": {
        "objectclasses": [
            "top", 
            "person", 
            "organizationalPerson", 
            "inetOrgPerson"
        ],
        "mappings": {
            "cn": "name",
            "description": "description",
            "displayname": "name",
            "facsimiletelephonenumber": "fax",
            "givenname": "firstname",
            "mail": "email",
            "telephonenumber": "phone",
            "title": "title",
            "sn": "lastname",
            "uid": "id"
        }
    }
}